sphinxcontrib/__init__.py
sphinxcontrib/pylit/__init__.py
sphinxcontrib_pylit-0.0.1.dist-info/METADATA
sphinxcontrib_pylit-0.0.1.dist-info/WHEEL
sphinxcontrib_pylit-0.0.1.dist-info/top_level.txt
sphinxcontrib_pylit-0.0.1.dist-info/RECORD
