Metadata-Version: 2.1
Name: sphinxcontrib-pylit
Version: 0.0.1
Summary: Literate Programming extension for Sphinx
Home-page: https://github.com/rblack42/sphinxcontrib-pylit
Author: Roie R. Black
Author-email: roie.black@gmail.com
License: BSD
Platform: UNKNOWN
